gloria/__init__.py
gloria/gloria_to_nc.py
gloria/gloria_to_txt.py
gloria/plot_gloria.py
gloria/read_gloria.py
gloria/write_gloria.py
bas_gloria-0.2.0.dist-info/entry_points.txt
bas_gloria-0.2.0.dist-info/LICENSE
bas_gloria-0.2.0.dist-info/WHEEL
bas_gloria-0.2.0.dist-info/METADATA
bas_gloria-0.2.0.dist-info/RECORD
