Metadata-Version: 2.1
Name: bas-gloria
Version: 0.2.0
Summary: Package for working with GLORIA side-scan sonar files
Home-page: https://github.com/antarctica/bas-gloria
License: Apache-2.0
Author: Paul Breen
Author-email: pbree@bas.ac.uk
Requires-Python: >=3.7,<4.0
Classifier: License :: OSI Approved :: Apache Software License
Classifier: Programming Language :: Python :: 3
Classifier: Programming Language :: Python :: 3.7
Classifier: Programming Language :: Python :: 3.8
Classifier: Programming Language :: Python :: 3.9
Requires-Dist: matplotlib (>=3.4.3,<4.0.0)
Requires-Dist: netCDF4 (>=1.5.2,<2.0.0)
Requires-Dist: numpy (>=1.17.2,<2.0.0)
Project-URL: Documentation, https://github.com/antarctica/bas-gloria/blob/main/README.md
Project-URL: Repository, https://github.com/antarctica/bas-gloria
